{
  "version": 1,
  "localAgentId": "agent_e09fdbb3d41c6d28",
  "bindingId": "0ba6d410-82ef-40e9-bfa3-fade4af49a47",
  "scopeSessionId": null,
  "organizationId": "org_64c8a438-f001-7065-b857-38eaf45bc24a",
  "organizationSlug": "saydeploy",
  "organizationName": "SayDeploy",
  "userId": "64c8a438-f001-7065-b857-38eaf45bc24a",
  "userEmail": "blogitech@gmail.com",
  "workspaceId": "ws_180b4af56f744056856c5d193264ce3f",
  "workspaceSlug": "imdbwatch",
  "workspaceName": "imdbwatch",
  "isSharedWorkspace": false,
  "sharedOwnerEmail": null,
  "clientKind": "vscode",
  "workspaceRootFingerprint": "ecfbc5979601e0d6",
  "workspaceRootLabel": "imdbwatch",
  "status": "unlinked",
  "lastRemoteSyncAt": null,
  "lastCredentialMigrationAt": null,
  "localVaultFingerprint": "5d2e722b8fa6c3ed",
  "remoteVaultCursor": null,
  "pendingWorkspaceRename": null
}
